openabc/__init__.py
openabc/forcefields/__init__.py
openabc/forcefields/cg_model.py
openabc/forcefields/hps_model.py
openabc/forcefields/hps_zero_offset_model.py
openabc/forcefields/moff_mrg_model.py
openabc/forcefields/moff_neat_dna_model.py
openabc/forcefields/mpipi_model.py
openabc/forcefields/mpipi_zero_offset_model.py
openabc/forcefields/rigid.py
openabc/forcefields/smog_3spn2_model.py
openabc/forcefields/__pycache__/__init__.cpython-313.pyc
openabc/forcefields/__pycache__/cg_model.cpython-313.pyc
openabc/forcefields/__pycache__/hps_model.cpython-313.pyc
openabc/forcefields/__pycache__/moff_mrg_model.cpython-313.pyc
openabc/forcefields/__pycache__/moff_neat_dna_model.cpython-313.pyc
openabc/forcefields/__pycache__/rigid.cpython-313.pyc
openabc/forcefields/functional_terms/__init__.py
openabc/forcefields/functional_terms/angle_terms.py
openabc/forcefields/functional_terms/bond_terms.py
openabc/forcefields/functional_terms/compound_bond_terms.py
openabc/forcefields/functional_terms/dihedral_terms.py
openabc/forcefields/functional_terms/hbond_terms.py
openabc/forcefields/functional_terms/nonbonded_terms.py
openabc/forcefields/functional_terms/zero_offset_nonbonded_terms.py
openabc/forcefields/functional_terms/__pycache__/__init__.cpython-313.pyc
openabc/forcefields/functional_terms/__pycache__/angle_terms.cpython-313.pyc
openabc/forcefields/functional_terms/__pycache__/bond_terms.cpython-313.pyc
openabc/forcefields/functional_terms/__pycache__/compound_bond_terms.cpython-313.pyc
openabc/forcefields/functional_terms/__pycache__/dihedral_terms.cpython-313.pyc
openabc/forcefields/functional_terms/__pycache__/hbond_terms.cpython-313.pyc
openabc/forcefields/functional_terms/__pycache__/nonbonded_terms.cpython-313.pyc
openabc/forcefields/parameters/3SPN2.conf
openabc/forcefields/parameters/HPS_KR_parameters.csv
openabc/forcefields/parameters/HPS_Urry_parameters.csv
openabc/forcefields/parameters/MOFF_contact_parameters.csv
openabc-1.0.8.dist-info/licenses/LICENSE
openabc-1.0.8.dist-info/METADATA
openabc-1.0.8.dist-info/WHEEL
openabc-1.0.8.dist-info/top_level.txt
openabc-1.0.8.dist-info/RECORD
