Metadata-Version: 2.4
Name: openabc
Version: 1.0.8
Classifier: Programming Language :: Python :: 3
Classifier: License :: OSI Approved :: MIT License
Classifier: Operating System :: OS Independent
Requires-Python: >=3.6
License-File: LICENSE
Requires-Dist: numpy
Requires-Dist: pandas
Requires-Dist: mdtraj
Requires-Dist: MDAnalysis
Requires-Dist: OpenMM
Requires-Dist: networkx
Dynamic: license-file
